{"errors":[],"warnings":[],"namedChunkGroups":{"app":{"chunks":[6,4,5,0],"assets":["webpack-runtime-35e21e3dced83ac19430.js","webpack-runtime-35e21e3dced83ac19430.js.map","framework-416331589561e92d1ff7.js","framework-416331589561e92d1ff7.js.map","styles.2543ff947a193d7f33b1.css","styles-ce7d9461498df738dc6a.js","styles-ce7d9461498df738dc6a.js.map","app-4b9b31efc3ddeb18d815.js","app-4b9b31efc3ddeb18d815.js.map"],"children":{},"childAssets":{}},"component---docs-index-mdx":{"chunks":[1,2],"assets":["bac1b955-98d1c1de9194467dcfea.js","bac1b955-98d1c1de9194467dcfea.js.map","component---docs-index-mdx-f78a26df59e1df84566f.js","component---docs-index-mdx-f78a26df59e1df84566f.js.map"],"children":{},"childAssets":{}},"component---src-pages-404-js":{"chunks":[3],"assets":["component---src-pages-404-js-a41f44259a22ab81ce37.js","component---src-pages-404-js-a41f44259a22ab81ce37.js.map"],"children":{},"childAssets":{}}},"assetsByChunkName":{"app":["webpack-runtime-35e21e3dced83ac19430.js","framework-416331589561e92d1ff7.js","styles.2543ff947a193d7f33b1.css","styles-ce7d9461498df738dc6a.js","app-4b9b31efc3ddeb18d815.js"],"component---docs-index-mdx":["bac1b955-98d1c1de9194467dcfea.js","component---docs-index-mdx-f78a26df59e1df84566f.js"],"component---src-pages-404-js":["component---src-pages-404-js-a41f44259a22ab81ce37.js"]}}